HlightReaxMD/__init__.py
HlightReaxMD/__init__.pyc
HlightReaxMD/analysis.pyc
HlightReaxMD/bondorder.pyc
HlightReaxMD/cascade.pyc
HlightReaxMD/collect.pyc
HlightReaxMD/datagen.pyc
HlightReaxMD/drawpng.pyc
HlightReaxMD/dump2bond.cp310-win_amd64.pyd
HlightReaxMD/findfile.pyc
HlightReaxMD/findspecies.pyc
HlightReaxMD/hlightreaxmd.pyc
HlightReaxMD/log.pyc
HlightReaxMD/mpi.pyc
HlightReaxMD/parserrun.pyc
HlightReaxMD/path.pyc
HlightReaxMD/reaction.pyc
HlightReaxMD/repository.pyc
HlightReaxMD/shell.pyc
HlightReaxMD/tips.pyc
HlightReaxMD/hbond/__init__.py
HlightReaxMD/hbond/__init__.pyc
HlightReaxMD/hbond/hbond.pyc
HlightReaxMD/mlpkg/__init__.py
HlightReaxMD/mlpkg/__init__.pyc
HlightReaxMD/mlpkg/complete_workflow.pyc
HlightReaxMD/mlpkg/config.json
HlightReaxMD/mlpkg/fp_analyzer.pyc
HlightReaxMD/mlpkg/prediction.pyc
HlightReaxMD/mlpkg/radchemml/__init__.py
HlightReaxMD/mlpkg/radchemml/__init__.pyc
HlightReaxMD/mlpkg/radchemml/cli.pyc
HlightReaxMD/mlpkg/radchemml/config.pyc
HlightReaxMD/mlpkg/radchemml/predict.pyc
HlightReaxMD/mlpkg/radchemml/train.pyc
HlightReaxMD/mlpkg/radchemml/workflow.pyc
HlightReaxMD/mlpkg/radchemml/models/__init__.py
HlightReaxMD/mlpkg/radchemml/models/__init__.pyc
HlightReaxMD/mlpkg/radchemml/models/xgboost_model.pyc
HlightReaxMD/mlpkg/radchemml/preprocessing/__init__.py
HlightReaxMD/mlpkg/radchemml/preprocessing/__init__.pyc
HlightReaxMD/mlpkg/radchemml/preprocessing/preprocessor.pyc
HlightReaxMD/mlpkg/radchemml/visualization/__init__.py
HlightReaxMD/mlpkg/radchemml/visualization/__init__.pyc
HlightReaxMD/mlpkg/radchemml/visualization/fingerprint_analyzer.pyc
HlightReaxMD/mlpkg/radchemml/visualization/performance_report.pyc
HlightReaxMD/tools/__init__.py
HlightReaxMD/tools/__init__.pyc
HlightReaxMD/tools/coarsegraining.pyc
HlightReaxMD/tools/elastic.pyc
HlightReaxMD/tools/fixspecies_rate.pyc
HlightReaxMD/tools/onlyExtractbonds.pyc
HlightReaxMD/tools/onlyExtractmols.pyc
HlightReaxMD/tools/only_Active_energy .pyc
HlightReaxMD/tools/only_drawSMILES.pyc
HlightReaxMD-1.5.0.9.dist-info/LICENSE
HlightReaxMD-1.5.0.9.dist-info/METADATA
HlightReaxMD-1.5.0.9.dist-info/WHEEL
HlightReaxMD-1.5.0.9.dist-info/dependency_links.txt
HlightReaxMD-1.5.0.9.dist-info/top_level.txt
HlightReaxMD-1.5.0.9.dist-info/RECORD
