Metadata-Version: 2.1
Name: HlightReaxMD
Version: 1.5.0.9
Summary: Projects for analysis of cascade collision processes and molecular chemical reactions
Home-page: https://gitee.com/zai-xia/HlightReaxMD
Author: W.-Y.Li, RFUE
Author-email: bestleeimpact@163.com
License: Proprietary
Classifier: Development Status :: 5 - Production/Stable
Classifier: Intended Audience :: Science/Research
Classifier: License :: Other/Proprietary License
Classifier: Programming Language :: Python :: 3
Classifier: Programming Language :: Python :: 3.9
Classifier: Programming Language :: Python :: 3.10
Classifier: Programming Language :: Python :: 3.11
Classifier: Operating System :: OS Independent
Classifier: Topic :: Scientific/Engineering :: Chemistry
Classifier: Topic :: Scientific/Engineering :: Physics
Requires-Python: >=3.9
License-File: LICENSE
Requires-Dist: alive-progress
Requires-Dist: ase
Requires-Dist: CairoSVG==2.7.1
Requires-Dist: graphviz
Requires-Dist: lz4
Requires-Dist: mpi4py
Requires-Dist: networkx
Requires-Dist: plotly==5.24.1
Requires-Dist: cufflinks
Requires-Dist: scikit-learn>=1.0.0
Requires-Dist: xgboost>=1.5.0
Requires-Dist: numpy>=1.24.3
Requires-Dist: pandas>=1.3.0
Requires-Dist: rdkit==2023.9.2
Requires-Dist: matplotlib>=3.4.0
Requires-Dist: seaborn>=0.11.0
Requires-Dist: shap>=0.40.0
Requires-Dist: scikit-optimize>=0.9.0
Requires-Dist: joblib>=1.1.0
Requires-Dist: pyyaml>=6.0
Requires-Dist: requests
Requires-Dist: scipy
Requires-Dist: tqdm
Requires-Dist: IPython
